CHANGELOG.rst
LICENSE
MANIFEST.in
README.rst
setup.py
test-requirements.txt
fedmsg.d/base.py
fedmsg.d/logging.py
fedmsg.d/pdcupdater-example.py
fedmsg.d/ssl.py
pdc_updater.egg-info/PKG-INFO
pdc_updater.egg-info/SOURCES.txt
pdc_updater.egg-info/dependency_links.txt
pdc_updater.egg-info/entry_points.txt
pdc_updater.egg-info/requires.txt
pdc_updater.egg-info/top_level.txt
pdcupdater/__init__.py
pdcupdater/commands.py
pdcupdater/consumer.py
pdcupdater/services.py
pdcupdater/utils.py
pdcupdater/handlers/__init__.py
pdcupdater/handlers/atomic.py
pdcupdater/handlers/compose.py
pdcupdater/handlers/modules.py
pdcupdater/handlers/persons.py
pdcupdater/handlers/pkgdb.py
pdcupdater/handlers/retirement.py
pdcupdater/handlers/rpms.py
pdcupdater/handlers/depchain/__init__.py
pdcupdater/handlers/depchain/base.py
pdcupdater/handlers/depchain/containers.py
pdcupdater/handlers/depchain/rpms.py
pdcupdater/tests/__init__.py
pdcupdater/tests/handler_tests/__init__.py
pdcupdater/tests/handler_tests/test_atomic.py
pdcupdater/tests/handler_tests/test_compose.py
pdcupdater/tests/handler_tests/test_depchain_containers.py
pdcupdater/tests/handler_tests/test_depchain_rpms.py
pdcupdater/tests/handler_tests/test_kerberos_auth.py
pdcupdater/tests/handler_tests/test_modules.py
pdcupdater/tests/handler_tests/test_persons.py
pdcupdater/tests/handler_tests/test_pkgdb.py
pdcupdater/tests/handler_tests/test_retirement.py
pdcupdater/tests/handler_tests/test_rpms.py
pdcupdater/tests/handler_tests/data/README
pdcupdater/tests/handler_tests/data/composeinfo.json
pdcupdater/tests/handler_tests/data/images.json
pdcupdater/tests/handler_tests/data/messagebus-example1.json
pdcupdater/tests/handler_tests/data/rpms.json
pdcupdater/tests/handler_tests/test_modules_data/modulemd.yaml
pdcupdater/tests/vcr-request-data/pdcupdater.tests.handler_tests.TestBaseHarness.test_get_fedmsg
pdcupdater/tests/vcr-request-data/pdcupdater.tests.handler_tests.TestBaseHarness.test_get_nonexistant_fedmsg
pdcupdater/tests/vcr-request-data/pdcupdater.tests.handler_tests.test_atomic.TestAtomicUpdate.test_cannot_handle_other_git_push
pdcupdater/tests/vcr-request-data/pdcupdater.tests.handler_tests.test_atomic.TestAtomicUpdate.test_handle_a_push
