Metadata-Version: 1.0
Name: pdc-updater
Version: 0.9.3
Summary: Update the product-definition-center in response to fedmsg
Home-page: https://github.com/fedora-infra/pdc-updater
Author: Ralph Bean
Author-email: rbean@redhat.com
License: GPLv2+
Platform: UNKNOWN
